setup.py
stringobject/__init__.py
stringobject/csharpstring.py
csharpstring-0.0.4.dist-info/METADATA
csharpstring-0.0.4.dist-info/WHEEL
csharpstring-0.0.4.dist-info/RECORD
