Metadata-Version: 2.1
Name: csharpstring
Version: 0.0.4
Summary: Adds a CSharp Style String Object, and namespace emulating much of the syntax C# uses to manipulate strings.
Project-URL: Homepage, https://github.com/Keepsedge/Python-Packages/tree/main
Project-URL: Bug Tracker, https://github.com/Keepsedge/Python-Packages/issues
Author-email: JSullivan <energy.keeper@gmail.com>
Classifier: License :: OSI Approved :: MIT License
Classifier: Operating System :: OS Independent
Classifier: Programming Language :: Python :: 3
Requires-Python: >=3.7
